PMcalcl/__init__.py
PMcalcl/main.py
PMcalc-0.1.1.dist-info/LICENSE
PMcalc-0.1.1.dist-info/METADATA
PMcalc-0.1.1.dist-info/WHEEL
PMcalc-0.1.1.dist-info/top_level.txt
PMcalc-0.1.1.dist-info/RECORD
