Metadata-Version: 2.1
Name: PMcalc
Version: 0.1.1
Summary: Package for performing calculations with uncertainties
Home-page: https://github.com/skabrits/smartcalc
Author: Vsevolod Kabrits
Author-email: seva.kabrits@gmail.com
License: UNKNOWN
Platform: UNKNOWN
Classifier: Programming Language :: Python :: 3
Classifier: License :: OSI Approved :: MIT License
Classifier: Operating System :: OS Independent
Requires-Python: >=3.6
